clongen-2023.1001.dist-info/METADATA
clongen-2023.1001.dist-info/WHEEL
clongen-2023.1001.dist-info/entry_points.txt
clongen-2023.1001.dist-info/licenses/LICENSE
clongen/__init__.py
clongen/_version.py
clongen/cli.py
clongen/core.py
clongen/sequences.py
clongen/term.py
clongen-2023.1001.dist-info/RECORD
