Metadata-Version: 2.1
Name: clongen
Version: 2023.1001
Summary: clonmapper reference genome generator
Author-Email: Daylin Morgan <daylinmorgan@gmail.com>
License: MIT
Requires-Python: >=3.8
Requires-Dist: rich>=13.5.2
Requires-Dist: rich-click>=1.6.1
